deep_q_reg/__init__.py
deep_q_reg/test.py
deep_q_reg/parts/default_params.py
deep_q_reg/parts/utils.py
deep_q_reg-0.0.3.dist-info/METADATA
deep_q_reg-0.0.3.dist-info/WHEEL
deep_q_reg-0.0.3.dist-info/top_level.txt
deep_q_reg-0.0.3.dist-info/RECORD
