Metadata-Version: 2.1
Name: deep-q-reg
Version: 0.0.3
Summary: Tool to easily perform quantile regression using deep learning (pytorch).
Home-page: https://github.co.jp/
Author: bib_inf
Author-email: contact.bibinf@gmail.com
License: CC0 v1.0
Platform: UNKNOWN
Classifier: Programming Language :: Python :: 3
Classifier: License :: CC0 1.0 Universal (CC0 1.0) Public Domain Dedication
Requires-Dist: ezpip
Requires-Dist: sout (>=1.2.1)
Requires-Dist: relpath
Requires-Dist: fies
Requires-Dist: tqdm
Requires-Dist: eznorm
